{
  "menu": [
    {
      "img": "img/tabs/vegy.jpg",
      "altimg": "vegy",
      "title": "Меню 'Фитнес'",
      "descr": "Меню 'Фитнес' - это новый подход к приготовлению блюд: больше свежих овощей и фруктов. Продукт активных и здоровых людей. Это абсолютно новый продукт с оптимальной ценой и высоким качеством!",
      "price": 9
    },
    {
      "img": "img/tabs/post.jpg",
      "altimg": "post",
      "title": "Меню 'Постное'",
      "descr": "Меню 'Постное' - это тщательный подбор ингредиентов: полное отсутствие продуктов животного происхождения, молоко из миндаля, овса, кокоса или гречки, правильное количество белков за счет тофу и импортных вегетарианских стейков.",
      "price": 14
    },
    {
      "img": "img/tabs/elite.jpg",
      "altimg": "elite",
      "title": "Меню 'Премиум'",
      "descr": "В меню 'Премиум' мы используем не только красивый дизайн упаковки, но и качественное исполнение блюд. Красная рыба, морепродукты, фрукты - ресторанное меню без похода в ресторан!",
      "price": 21
    }
  ],
  "requests": [
    {
      "name": "sss",
      "phone": "k",
      "id": 32
    },
    {
      "name": "2012",
      "phone": "55465465",
      "id": 33
    },
    {
      "name": "sss",
      "phone": "scac",
      "id": 34
    },
    {
      "name": "sss",
      "phone": " lj hhjlblhblb",
      "id": 35
    },
    {
      "name": "Alex",
      "phone": "45666",
      "id": 36
    }
  ]
}